<?xml version="1.0" encoding="UTF-8" standalone="yes"?>
<records>
   <record>
      <manuscriptID>4209</manuscriptID>
      <signature>The Hague, KB, 79 K 2</signature>
      <signatureRegister>79 K 2</signatureRegister>
      <CommonsCatTitle>Book of Hours in Dutch</CommonsCatTitle>
      <contents>Book of Hours in Dutch</contents>
      <titleRegister>Book of Hours in Dutch</titleRegister>
      <locationDate>Utrecht, Masters of Zweder van Culemborg (illuminator); circa 1430-1435</locationDate>
      <country>Northern Netherlands</country>
      <locationRegister>Utrecht</locationRegister>
      <dateRegister>1430-1435</dateRegister>
      <miniaturistRegister>Masters of Zweder van Culemborg</miniaturistRegister>
      <borderDecoration>Utrecht decoration (bonte blaadjes)</borderDecoration>
      <borderDecoration>Utrecht penwork (vroege stijl)</borderDecoration>
      <illuminations>27 full-page miniatures (possibly 15 missing); 16 historiated initials; decorated initials with border decoration; penwork initials</illuminations>
      <provenance>Mabel Ward Savage (1884-1956). Probably owned by A.S.W. Rosenbach in the early 1920s. Private collection in the United States. Presented in 1998 by P. Fentener van Vlissingen on the occasion of the library&apos;s bicentennial as a 99-year loan</provenance>
      <provenanceRegister>Fentener van Vlissingen, P.</provenanceRegister>
      <literature>Utrecht/New York 1989, no. 34, pl. 34, fig. 51</literature>
      <literature>Facsimile KB 79 K 2 1999</literature>
      <literature>Marrow (forthcoming)</literature>
      <material>Vellum</material>
      <folia>ff. 155</folia>
      <dimensions>116x84 (68x43) mm</dimensions>
      <columns>1 column</columns>
      <lines>13 lines</lines>
      <script>Littera textualis</script>
      <language>Dutch</language>
      <binding>Binding: modern red velvet</binding>
      <foliumHeigth>116</foliumHeigth>
      <foliumWidth>84</foliumWidth>
      <blockHeigth>68</blockHeigth>
      <blockWidth>43</blockWidth>
      <earliestDate>1430</earliestDate>
      <latestDate>1435</latestDate>
      <lines2>13 lines</lines2>
      <dateRegisterIndex>1430-1435</dateRegisterIndex>
   </record>
</records>
